{
    "format_version": "1.21.50",
    "minecraft:block": {
        "description": {
            "identifier": "spimton:feral_soulsand",
            "menu_category": {
                "category": "nature"
            }
        },
        "components": {
            "minecraft:destructible_by_mining": {
                "seconds_to_destroy": 3,
                "item_specific_speeds": [
                    {
                        "item": {
                            "tags": "query.all_tags('minecraft:is_shovel','minecraft:iron_tier')"
                        },
                        "destroy_speed": 0.8
                    },
                    {
                        "item": {
                            "tags": "query.all_tags('minecraft:is_shovel','minecraft:stone_tier')"
                        },
                        "destroy_speed": 1
                    },
                    {
                        "item": {
                            "tags": "query.all_tags('minecraft:is_shovel','minecraft:wood_tier')"
                        },
                        "destroy_speed": 1.2
                    },
                    {
                        "item": {
                            "tags": "query.all_tags('minecraft:is_shovel','minecraft:diamond_tier')"
                        },
                        "destroy_speed": 0.4
                    },
                    {
                        "item": {
                            "tags": "query.all_tags('minecraft:is_shovel','minecraft:netherite_tier')"
                        },
                        "destroy_speed": 0.3
                    },
                    {
                        "item": {
                            "tags": "query.all_tags('minecraft:is_shovel','minecraft:golden_tier')"
                        },
                        "destroy_speed": 0.1
                    }
                ]
            },
            "minecraft:destructible_by_explosion": {
                "explosion_resistance": 3
            },
            "minecraft:custom_components": [
                "spimton:feral_soulsand"
            ],
            "minecraft:loot": "loot_tables/empty.json",
            "minecraft:map_color": "#F6E462",
            "minecraft:light_dampening": 15,
            "minecraft:light_emission": 7,
            "tag:minecraft:is_shovel_item_destructible": {},
            "tag:sand": {},
            "tag:iron": {},
            "tag:metal": {}
        }
    }
}