{
    "format_version": "1.21.40",
    "minecraft:recipe_shaped": {
        "description": {
            "identifier": "spimton:jade_spear"
        },
        "tags": [
            "crafting_table"
        ],
        "assume_symmetry": true,
        "unlock": {
            "context": "PlayerHasManyItems"
        },
        "pattern": [
            "  #",
            " o ",
            "@  "
        ],
        "key": {
            "#": {
                "item": "spimton:jade_cladding"
            },
            "@": {
                "item": "stick"
            },
            "o": {
                "item": "spimton:overgrown_orb"
            }
        },
        "result": {
            "item": "spimton:jade_spear"
        }
    }
}